setup.py
afx/__init__.py
afx/exceptions.py
afx/globals.py
afx/models.py
afx/table.py
afx.egg-info/PKG-INFO
afx.egg-info/SOURCES.txt
afx.egg-info/dependency_links.txt
afx.egg-info/requires.txt
afx.egg-info/top_level.txt